LICENSE
README.md
pyproject.toml
setup.cfg
setup.py
cypherx/__init__.py
cypherx/cli.py
cypherx/cypherx.py
cypherx.egg-info/PKG-INFO
cypherx.egg-info/SOURCES.txt
cypherx.egg-info/dependency_links.txt
cypherx.egg-info/entry_points.txt
cypherx.egg-info/requires.txt
cypherx.egg-info/top_level.txt
tests/__init__.py
tests/test_cypherx.py