Metadata-Version: 2.1
Name: cypherx
Version: 1.3
Summary: Ferramenta de criptografia e descriptografia de textos
Home-page: https://github.com/yuritorresf/cypherx
Author: Yuri Torres
Author-email: feereira@gmail.com
License: MIT
Project-URL: Código fonte, https://github.com/yuritorresf/cypherx
Project-URL: Bug Tracker, https://github.com/yuritorresf/cypherx/issues
Project-URL: Download, https://github.com/yuritorresf/cypherx/archive/1.3.zip
Keywords: cypherx,package,cryptography,cryptography package
Platform: UNKNOWN
Classifier: Development Status :: 5 - Production/Stable
Classifier: Intended Audience :: Developers
Classifier: License :: OSI Approved :: MIT License
Classifier: Natural Language :: Portuguese (Brazilian)
Classifier: Operating System :: OS Independent
Classifier: Topic :: Software Development :: Internationalization
Requires-Python: >=3.6.3
